iffnn/__init__.py
iffnn/model.py
iffnn-0.2.1.dist-info/licenses/LICENSE
iffnn-0.2.1.dist-info/METADATA
iffnn-0.2.1.dist-info/WHEEL
iffnn-0.2.1.dist-info/top_level.txt
iffnn-0.2.1.dist-info/RECORD
