Metadata-Version: 2.4
Name: iffnn
Version: 0.2.1
Summary: Interpretable Feedforward Neural Network Library based on Li et al.
Home-page: https://github.com/MilesQLi/iffnn
Author: Miles Q. Li
Author-email: miles.qi.li@mail.mcgill.ca
Project-URL: Documentation, https://github.com/MilesQLi/iffnn#readme
Project-URL: Source, https://github.com/MilesQLi/iffnn
Project-URL: Bug Tracker, https://github.com/MilesQLi/iffnn/issues
Keywords: interpretable neural networks explainability PyTorch AI
Classifier: Development Status :: 4 - Beta
Classifier: Programming Language :: Python :: 3
Classifier: License :: OSI Approved :: Apache Software License
Classifier: Operating System :: OS Independent
Classifier: Intended Audience :: Science/Research
Classifier: Intended Audience :: Developers
Classifier: Topic :: Scientific/Engineering :: Artificial Intelligence
Classifier: Topic :: Software Development :: Libraries :: Python Modules
Requires-Python: >=3.7
License-File: LICENSE
Requires-Dist: torch>=1.7.0
Requires-Dist: tqdm>=4.50.0
Provides-Extra: dev
Requires-Dist: pytest; extra == "dev"
Requires-Dist: flake8; extra == "dev"
Provides-Extra: examples
Requires-Dist: scikit-learn>=0.24.0; extra == "examples"
Dynamic: author
Dynamic: author-email
Dynamic: classifier
Dynamic: description
Dynamic: description-content-type
Dynamic: home-page
Dynamic: keywords
Dynamic: license-file
Dynamic: project-url
Dynamic: provides-extra
Dynamic: requires-dist
Dynamic: requires-python
Dynamic: summary
